Workbook

Sheet Guide
A1: STRUCTURED PRODUCTS — UNDERLYING PERFORMANCE CHART
A2: Reuters / LSEG feed · client-ready graphic · internal tool
A5: HOW TO USE — 4 STEPS
A6: 1 | B6: Go to 'Inputs' | C6: Type your Reuters RIC codes (e.g. .STOXX50E, .SPX, BNPP.PA), the display name for the legend, and the start / end dates. Yellow cells = the only cells you ever type in.
A7: 2 | B7: Refresh Reuters | C7: In the LSEG / Refinitiv ribbon click 'Refresh All' (or Ctrl+Alt+F9). The 'Data' sheet pulls the daily closing prices for every ticker.
A8: 3 | B8: Set the levels | C8: Still on 'Inputs': switch each product level ON/OFF (Strike, Autocall trigger, Coupon barrier, Capital barrier, plus 2 free lines), give it a label and a % of the initial fixing. They are drawn as dashed lines on the chart.
A9: 4 | B9: Go to 'Chart' | C9: That is the client deliverable. Change the title / subtitle / footnote on 'Inputs' and the chart updates. Right-click the chart > Copy, then paste into PowerPoint or Outlook as a picture. Or Ctrl+P > the sheet is already set to print one landscape page / PDF.
A11: WHAT MAKES THE DATA COHERENT
A12: • | B12: One single calendar | C12: Every ticker is mapped onto ONE common date axis (all weekdays between your start and end date). No ticker can shift the chart left or right, whatever holiday calendar it trades on.
A13: • | B13: No holes | C13: If a ticker did not trade on a given day (local holiday, suspension), the previous closing price is carried forward. The line stays continuous instead of collapsing to zero.
A14: • | B14: Same base | C14: All tickers are rebased to 100 at the SAME initial fixing date, so a 5-underlying worst-of is directly comparable. Switch to absolute prices on 'Inputs' if you only chart one underlying.
A15: • | B15: Quality panel | C15: 'Inputs' shows, per ticker: number of points, first / last date available, and the % of days carried forward. It also tells you the earliest date common to all your tickers — never start a chart before it.
A17: THE SHEETS
A18: Inputs | B18: You work here | C18: Tickers, period, scale, product levels, chart texts, data-quality panel.
A19: Chart | B19: Client deliverable | C19: The graphic only. Nothing to edit here.
A20: Data | B20: Reuters feed | C20: One block of Reuters formulas per ticker (date + close). Raw output, do not reformat.
A21: Calc | B21: Engine | C21: Common date axis, aligned prices, rebasing, level lines. Do not touch.
A22: Formulas | B22: Reference | C22: The exact Reuters/LSEG formulas used, alternatives (RHistory, total return, weekly/monthly) and troubleshooting.
A24: FINE-TUNING THE GRAPHIC
A25: • | B25: Unused legend entries | C25: Slots you did not fill appear in the legend as (unused). Click the legend once, click that entry once more, press Delete. It removes the label, not the series - clearing a RIC later brings it back.
A26: • | B26: Vertical scale | C26: Excel picks the scale automatically. To tighten or widen it, right-click the vertical axis > Format Axis > set Minimum / Maximum. Keeping the capital barrier visible is usually the constraint.
A27: • | B27: Date labels | C27: Right-click the date axis > Format Axis > Units to switch between months, quarters and years if the labels crowd.
A28: • | B28: Colours | C28: Click a line once, then Format > Shape Outline. The palette was chosen so the four barrier lines stay distinguishable in black and white.
A29: • | B29: Size | C29: Drag the chart corner. It is anchored to cell B5 and prints on one landscape page as it is.
A31: IMPORTANT
A32: ! | B32: Data shows NAME errors | C32: Means the LSEG/Refinitiv Excel add-in is not loaded on this machine. File > Options > Add-ins > enable it, then Refresh All. See the 'Formulas' sheet.
A33: ! | B33: Manual override | C33: No add-in? You can paste Date / Close straight into the Data blocks (column 1 = date, column 2 = close). Everything downstream keeps working.
A34: ! | B34: Before sending | C34: Check the quality panel is green, check the footnote and the disclaimer, and remove any unused legend entry (click it once, press Delete).
B36: Internal tool. Data source: LSEG / Refinitiv (Reuters). Not a research report.

Sheet Inputs
A1: INPUTS — CONTROL PANEL
A2: Type only in the yellow cells. Blue text = your input. Black = calculated.
A4: 1. UNDERLYINGS (leave a Reuters code blank to disable the slot)
B5: Reuters code (RIC) | C5: Name shown in legend | D5: Points loaded | E5: First date | F5: Last date | G5: % days carried fwd | H5: Status | J5: legend text
A6: 1 | B6: .STOXX50E | C6: EURO STOXX 50 | D6: =IF($B6="","",COUNT(Data!$A$10:$A$3209)) | E6: =IF($D6="","",IF($D6=0,"",INT(MIN(Data!$A$10:$A$3209)))) | F6: =IF($D6="","",IF($D6=0,"",INT(MAX(Data!$A$10:$A$3209)))) | G6: =IF($B6="","",IF(SUM(Calc!$B$11:$B$2610)=0,"",1-SUM(Calc!$AD$11:$AD$2610)/SUM(Calc!$B$11:$B$2610))) | H6: =IF($B6="","not used",IF($D6=0,"NO DATA - check the RIC, then Refresh All",IF($E6>$C$14,"HISTORY STARTS "&TEXT($E6,"dd-mmm-yy")&" - move the start date",IF($F6<$C$15-7,"STALE - last quote "&TEXT($F6,"dd-mmm-yy"),IF($G6>0.15,"OK - but many carried days","OK"))))) | J6: =IF($B6="","(unused)",IF($C6="",$B6,$C6))
A7: 2 | B7: .SPX | C7: S&P 500 | D7: =IF($B7="","",COUNT(Data!$E$10:$E$3209)) | E7: =IF($D7="","",IF($D7=0,"",INT(MIN(Data!$E$10:$E$3209)))) | F7: =IF($D7="","",IF($D7=0,"",INT(MAX(Data!$E$10:$E$3209)))) | G7: =IF($B7="","",IF(SUM(Calc!$B$11:$B$2610)=0,"",1-SUM(Calc!$AE$11:$AE$2610)/SUM(Calc!$B$11:$B$2610))) | H7: =IF($B7="","not used",IF($D7=0,"NO DATA - check the RIC, then Refresh All",IF($E7>$C$14,"HISTORY STARTS "&TEXT($E7,"dd-mmm-yy")&" - move the start date",IF($F7<$C$15-7,"STALE - last quote "&TEXT($F7,"dd-mmm-yy"),IF($G7>0.15,"OK - but many carried days","OK"))))) | J7: =IF($B7="","(unused)",IF($C7="",$B7,$C7))
A8: 3 | D8: =IF($B8="","",COUNT(Data!$I$10:$I$3209)) | E8: =IF($D8="","",IF($D8=0,"",INT(MIN(Data!$I$10:$I$3209)))) | F8: =IF($D8="","",IF($D8=0,"",INT(MAX(Data!$I$10:$I$3209)))) | G8: =IF($B8="","",IF(SUM(Calc!$B$11:$B$2610)=0,"",1-SUM(Calc!$AF$11:$AF$2610)/SUM(Calc!$B$11:$B$2610))) | H8: =IF($B8="","not used",IF($D8=0,"NO DATA - check the RIC, then Refresh All",IF($E8>$C$14,"HISTORY STARTS "&TEXT($E8,"dd-mmm-yy")&" - move the start date",IF($F8<$C$15-7,"STALE - last quote "&TEXT($F8,"dd-mmm-yy"),IF($G8>0.15,"OK - but many carried days","OK"))))) | J8: =IF($B8="","(unused)",IF($C8="",$B8,$C8))
A9: 4 | D9: =IF($B9="","",COUNT(Data!$M$10:$M$3209)) | E9: =IF($D9="","",IF($D9=0,"",INT(MIN(Data!$M$10:$M$3209)))) | F9: =IF($D9="","",IF($D9=0,"",INT(MAX(Data!$M$10:$M$3209)))) | G9: =IF($B9="","",IF(SUM(Calc!$B$11:$B$2610)=0,"",1-SUM(Calc!$AG$11:$AG$2610)/SUM(Calc!$B$11:$B$2610))) | H9: =IF($B9="","not used",IF($D9=0,"NO DATA - check the RIC, then Refresh All",IF($E9>$C$14,"HISTORY STARTS "&TEXT($E9,"dd-mmm-yy")&" - move the start date",IF($F9<$C$15-7,"STALE - last quote "&TEXT($F9,"dd-mmm-yy"),IF($G9>0.15,"OK - but many carried days","OK"))))) | J9: =IF($B9="","(unused)",IF($C9="",$B9,$C9))
A10: 5 | D10: =IF($B10="","",COUNT(Data!$Q$10:$Q$3209)) | E10: =IF($D10="","",IF($D10=0,"",INT(MIN(Data!$Q$10:$Q$3209)))) | F10: =IF($D10="","",IF($D10=0,"",INT(MAX(Data!$Q$10:$Q$3209)))) | G10: =IF($B10="","",IF(SUM(Calc!$B$11:$B$2610)=0,"",1-SUM(Calc!$AH$11:$AH$2610)/SUM(Calc!$B$11:$B$2610))) | H10: =IF($B10="","not used",IF($D10=0,"NO DATA - check the RIC, then Refresh All",IF($E10>$C$14,"HISTORY STARTS "&TEXT($E10,"dd-mmm-yy")&" - move the start date",IF($F10<$C$15-7,"STALE - last quote "&TEXT($F10,"dd-mmm-yy"),IF($G10>0.15,"OK - but many carried days","OK"))))) | J10: =IF($B10="","(unused)",IF($C10="",$B10,$C10))
A12: 2. PERIOD & SCALE
B14: Start date | C14: =EDATE(TODAY(),-36) | D14: First date on the chart
B15: End date | C15: =TODAY() | D15: Last date on the chart
B16: Initial fixing date | C16: =$C$14 | D16: Strike date of the product: every underlying = 100 here
B17: Scale | C17: Rebased to 100 | D17: Rebased to 100 = compare several underlyings. Absolute price = one underlying only.
B18: Show worst-of line | C18: No | D18: Adds the minimum of all active underlyings - the worst-of used in the payoff
B19: Worst-of legend name | C19: Worst-of basket | D19: Text shown in the legend for that line | J19: =IF($C$18<>"Yes","(unused)",IF($C$19="","Worst-of",$C$19))
B20: Earliest date common to all | C20: =IF(COUNT($E$6:$E$10)=0,"",MAX($E$6:$E$10)) | D20: Never set the start date before this: a shorter history would be rebased on a missing price.
A22: 3. PRODUCT LEVELS (drawn as dashed lines on the chart)
B23: Show? | C23: Label on the chart | D23: % of initial | E23: Plotted at | F23: Line colour | H23: Typical use | J23: legend text
B24: No | C24: Initial level 100% | D24: 1 | E24: =IF($B24<>"Yes","",$D24*$C$35) | F24: Black | H24: Strike / initial fixing - redundant if the autocall sits at 100% | J24: =IF($B24<>"Yes","(unused)",IF($C24="","Level "&ROW()-23,$C24))
B25: Yes | C25: Autocall trigger 100% | D25: 1 | E25: =IF($B25<>"Yes","",$D25*$C$35) | F25: Green | H25: Early redemption barrier, observed on the recall dates | J25: =IF($B25<>"Yes","(unused)",IF($C25="","Level "&ROW()-23,$C25))
B26: Yes | C26: Coupon barrier 70% | D26: 0.7 | E26: =IF($B26<>"Yes","",$D26*$C$35) | F26: Gold | H26: Memory / conditional coupon barrier | J26: =IF($B26<>"Yes","(unused)",IF($C26="","Level "&ROW()-23,$C26))
B27: Yes | C27: Capital barrier 60% | D27: 0.6 | E27: =IF($B27<>"Yes","",$D27*$C$35) | F27: Red | H27: European or American knock-in on capital | J27: =IF($B27<>"Yes","(unused)",IF($C27="","Level "&ROW()-23,$C27))
B28: No | C28: Custom level 1 | D28: 0.8 | E28: =IF($B28<>"Yes","",$D28*$C$35) | F28: Purple | H28: Step-down, cap, protection floor, entry level... | J28: =IF($B28<>"Yes","(unused)",IF($C28="","Level "&ROW()-23,$C28))
B29: No | C29: Custom level 2 | D29: 1.2 | E29: =IF($B29<>"Yes","",$D29*$C$35) | F29: Grey | H29: Free line | J29: =IF($B29<>"Yes","(unused)",IF($C29="","Level "&ROW()-23,$C29))
A31: 4. CHART TEXTS
B32: Chart title | C32: EURO STOXX 50 vs S&P 500 - historical performance
B33: Subtitle | C33: Daily closing prices, rebased to 100 at the initial fixing date
B34: Footnote / source | C34: ="Source: LSEG / Refinitiv - daily closing prices, "&TEXT($C$14,"dd mmm yyyy")&" to "&TEXT($C$15,"dd mmm yyyy")&". Past performance is not a reliable indicator of future performance."
B35: Chart base value | C35: =IF($C$17="Rebased to 100",100,IF(N(Calc!$C$8)=0,100,Calc!$C$8)) | D35: 100 when rebased, otherwise the initial price of underlying 1. The levels above are a % of this.
B37: Full title fed to the chart | C37: =$C$32&CHAR(10)&$C$33
B38: Y-axis title fed to the chart | C38: =IF($C$17="Rebased to 100","Performance rebased to 100","Price level")
B40: Points plotted | C40: =SUM(Calc!$B$11:$B$2610)
B41: Maximum available | C41: 2600 | D41: =IF($C$40>=$C$41,"PERIOD TOO LONG - the chart stops after "&$C$41&" weekdays (about 10 years). Shorten the period.","About 10 years of weekdays - period fits.")

Sheet Data
A1: DATA — REUTERS / LSEG FEED
A2: Raw output of the add-in. Column 1 = date, column 2 = closing price. Do not insert rows or columns.
A4: UNDERLYING 1 | E4: UNDERLYING 2 | I4: UNDERLYING 3 | M4: UNDERLYING 4 | Q4: UNDERLYING 5
A5: =Inputs!$B$6 | E5: =Inputs!$B$7 | I5: =Inputs!$B$8 | M5: =Inputs!$B$9 | Q5: =Inputs!$B$10
A6: =Inputs!$C$6 | E6: =Inputs!$C$7 | I6: =Inputs!$C$8 | M6: =Inputs!$C$9 | Q6: =Inputs!$C$10
A8: =IF(Inputs!$B$6="","slot not used",COUNT(A10:A3209)&" points") | E8: =IF(Inputs!$B$7="","slot not used",COUNT(E10:E3209)&" points") | I8: =IF(Inputs!$B$8="","slot not used",COUNT(I10:I3209)&" points") | M8: =IF(Inputs!$B$9="","slot not used",COUNT(M10:M3209)&" points") | Q8: =IF(Inputs!$B$10="","slot not used",COUNT(Q10:Q3209)&" points")
A9: ↓ Reuters formulas below (red). Refresh with the LSEG ribbon > Refresh All, or Ctrl+Alt+F9.
A10: =IF(Inputs!$B$6="","",@TR(Inputs!$B$6,"TR.PriceClose.date;TR.PriceClose","SDate="&TEXT(Inputs!$C$14,"yyyy-mm-dd")&" EDate="&TEXT(Inputs!$C$15,"yyyy-mm-dd")&" Frq=D CH=Fd RH=IN Null=Skip")) | E10: =IF(Inputs!$B$7="","",@TR(Inputs!$B$7,"TR.PriceClose.date;TR.PriceClose","SDate="&TEXT(Inputs!$C$14,"yyyy-mm-dd")&" EDate="&TEXT(Inputs!$C$15,"yyyy-mm-dd")&" Frq=D CH=Fd RH=IN Null=Skip")) | I10: =IF(Inputs!$B$8="","",@TR(Inputs!$B$8,"TR.PriceClose.date;TR.PriceClose","SDate="&TEXT(Inputs!$C$14,"yyyy-mm-dd")&" EDate="&TEXT(Inputs!$C$15,"yyyy-mm-dd")&" Frq=D CH=Fd RH=IN Null=Skip")) | M10: =IF(Inputs!$B$9="","",@TR(Inputs!$B$9,"TR.PriceClose.date;TR.PriceClose","SDate="&TEXT(Inputs!$C$14,"yyyy-mm-dd")&" EDate="&TEXT(Inputs!$C$15,"yyyy-mm-dd")&" Frq=D CH=Fd RH=IN Null=Skip")) | Q10: =IF(Inputs!$B$10="","",@TR(Inputs!$B$10,"TR.PriceClose.date;TR.PriceClose","SDate="&TEXT(Inputs!$C$14,"yyyy-mm-dd")&" EDate="&TEXT(Inputs!$C$15,"yyyy-mm-dd")&" Frq=D CH=Fd RH=IN Null=Skip"))

Sheet Calc
A1: CALC — ENGINE (do not edit)
A2: Common weekday calendar · alignment of every ticker on it · carry-forward · rebasing · level lines.
A7: Fixing row | B7: =MAX(1,MIN(IFERROR(MATCH(Inputs!$C$16,$A$11:$A$2610,1),1),MAX(1,SUM($B$11:$B$2610))))
A8: Initial px | C8: =IF(Inputs!$B$6="","",IFERROR(INDEX($C$11:$C$2610,$B$7),"")) | D8: =IF(Inputs!$B$7="","",IFERROR(INDEX($D$11:$D$2610,$B$7),"")) | E8: =IF(Inputs!$B$8="","",IFERROR(INDEX($E$11:$E$2610,$B$7),"")) | F8: =IF(Inputs!$B$9="","",IFERROR(INDEX($F$11:$F$2610,$B$7),"")) | G8: =IF(Inputs!$B$10="","",IFERROR(INDEX($G$11:$G$2610,$B$7),""))
A9: Base | B9: =Inputs!$C$35
A10: Date (common axis) | B10: Used? | C10: Px 1 | D10: Px 2 | E10: Px 3 | F10: Px 4 | G10: Px 5 | I10: PLOT 1 | J10: PLOT 2 | K10: PLOT 3 | L10: PLOT 4 | M10: PLOT 5 | N10: WORST-OF | O10: LEVEL 1 | P10: LEVEL 2 | Q10: LEVEL 3 | R10: LEVEL 4 | S10: LEVEL 5 | T10: LEVEL 6 | AD10: hit 1 | AE10: hit 2 | AF10: hit 3 | AG10: hit 4 | AH10: hit 5
A11: =IF(WEEKDAY(Inputs!$C$14,2)>5,Inputs!$C$14+8-WEEKDAY(Inputs!$C$14,2),Inputs!$C$14) | B11: 1 | C11: =IF($B11=0,"",IF(Inputs!$B$6="","",IF($AD11=0,"",SUMIFS(Data!$B$10:$B$3209,Data!$A$10:$A$3209,">="&$A11,Data!$A$10:$A$3209,"<"&$A11+1)/$AD11))) | D11: =IF($B11=0,"",IF(Inputs!$B$7="","",IF($AE11=0,"",SUMIFS(Data!$F$10:$F$3209,Data!$E$10:$E$3209,">="&$A11,Data!$E$10:$E$3209,"<"&$A11+1)/$AE11))) | E11: =IF($B11=0,"",IF(Inputs!$B$8="","",IF($AF11=0,"",SUMIFS(Data!$J$10:$J$3209,Data!$I$10:$I$3209,">="&$A11,Data!$I$10:$I$3209,"<"&$A11+1)/$AF11))) | F11: =IF($B11=0,"",IF(Inputs!$B$9="","",IF($AG11=0,"",SUMIFS(Data!$N$10:$N$3209,Data!$M$10:$M$3209,">="&$A11,Data!$M$10:$M$3209,"<"&$A11+1)/$AG11))) | G11: =IF($B11=0,"",IF(Inputs!$B$10="","",IF($AH11=0,"",SUMIFS(Data!$R$10:$R$3209,Data!$Q$10:$Q$3209,">="&$A11,Data!$Q$10:$Q$3209,"<"&$A11+1)/$AH11))) | I11: =IF($B11=0,NA(),IF($C11="",NA(),IF(C$8="",NA(),IF(N(C$8)=0,NA(),IF(Inputs!$C$17="Rebased to 100",$C11/C$8*100,$C11))))) | J11: =IF($B11=0,NA(),IF($D11="",NA(),IF(D$8="",NA(),IF(N(D$8)=0,NA(),IF(Inputs!$C$17="Rebased to 100",$D11/D$8*100,$D11))))) | K11: =IF($B11=0,NA(),IF($E11="",NA(),IF(E$8="",NA(),IF(N(E$8)=0,NA(),IF(Inputs!$C$17="Rebased to 100",$E11/E$8*100,$E11))))) | L11: =IF($B11=0,NA(),IF($F11="",NA(),IF(F$8="",NA(),IF(N(F$8)=0,NA(),IF(Inputs!$C$17="Rebased to 100",$F11/F$8*100,$F11))))) | M11: =IF($B11=0,NA(),IF($G11="",NA(),IF(G$8="",NA(),IF(N(G$8)=0,NA(),IF(Inputs!$C$17="Rebased to 100",$G11/G$8*100,$G11))))) | N11: =IF($B11=0,NA(),IF(Inputs!$C$18<>"Yes",NA(),IF(COUNT(I11,J11,K11,L11,M11)=0,NA(),MIN(I11,J11,K11,L11,M11)))) | O11: =IF($B11=0,NA(),IF(Inputs!$B$24<>"Yes",NA(),Inputs!$D$24*Inputs!$C$35)) | P11: =IF($B11=0,NA(),IF(Inputs!$B$25<>"Yes",NA(),Inputs!$D$25*Inputs!$C$35)) | Q11: =IF($B11=0,NA(),IF(Inputs!$B$26<>"Yes",NA(),Inputs!$D$26*Inputs!$C$35)) | R11: =IF($B11=0,NA(),IF(Inputs!$B$27<>"Yes",NA(),Inputs!$D$27*Inputs!$C$35)) | S11: =IF($B11=0,NA(),IF(Inputs!$B$28<>"Yes",NA(),Inputs!$D$28*Inputs!$C$35)) | T11: =IF($B11=0,NA(),IF(Inputs!$B$29<>"Yes",NA(),Inputs!$D$29*Inputs!$C$35)) | AD11: =IF($B11=0,0,IF(Inputs!$B$6="",0,COUNTIFS(Data!$A$10:$A$3209,">="&$A11,Data!$A$10:$A$3209,"<"&$A11+1))) | AE11: =IF($B11=0,0,IF(Inputs!$B$7="",0,COUNTIFS(Data!$E$10:$E$3209,">="&$A11,Data!$E$10:$E$3209,"<"&$A11+1))) | AF11: =IF($B11=0,0,IF(Inputs!$B$8="",0,COUNTIFS(Data!$I$10:$I$3209,">="&$A11,Data!$I$10:$I$3209,"<"&$A11+1))) | AG11: =IF($B11=0,0,IF(Inputs!$B$9="",0,COUNTIFS(Data!$M$10:$M$3209,">="&$A11,Data!$M$10:$M$3209,"<"&$A11+1))) | AH11: =IF($B11=0,0,IF(Inputs!$B$10="",0,COUNTIFS(Data!$Q$10:$Q$3209,">="&$A11,Data!$Q$10:$Q$3209,"<"&$A11+1)))
A12: =MIN(Inputs!$C$15,$A11+IF(WEEKDAY($A11,2)=5,3,1)) | B12: =IF($A12>$A11,1,0) | C12: =IF($B12=0,"",IF(Inputs!$B$6="","",IF($AD12=0,C11,SUMIFS(Data!$B$10:$B$3209,Data!$A$10:$A$3209,">="&$A12,Data!$A$10:$A$3209,"<"&$A12+1)/$AD12))) | D12: =IF($B12=0,"",IF(Inputs!$B$7="","",IF($AE12=0,D11,SUMIFS(Data!$F$10:$F$3209,Data!$E$10:$E$3209,">="&$A12,Data!$E$10:$E$3209,"<"&$A12+1)/$AE12))) | E12: =IF($B12=0,"",IF(Inputs!$B$8="","",IF($AF12=0,E11,SUMIFS(Data!$J$10:$J$3209,Data!$I$10:$I$3209,">="&$A12,Data!$I$10:$I$3209,"<"&$A12+1)/$AF12))) | F12: =IF($B12=0,"",IF(Inputs!$B$9="","",IF($AG12=0,F11,SUMIFS(Data!$N$10:$N$3209,Data!$M$10:$M$3209,">="&$A12,Data!$M$10:$M$3209,"<"&$A12+1)/$AG12))) | G12: =IF($B12=0,"",IF(Inputs!$B$10="","",IF($AH12=0,G11,SUMIFS(Data!$R$10:$R$3209,Data!$Q$10:$Q$3209,">="&$A12,Data!$Q$10:$Q$3209,"<"&$A12+1)/$AH12))) | I12: =IF($B12=0,NA(),IF($C12="",NA(),IF(C$8="",NA(),IF(N(C$8)=0,NA(),IF(Inputs!$C$17="Rebased to 100",$C12/C$8*100,$C12))))) | J12: =IF($B12=0,NA(),IF($D12="",NA(),IF(D$8="",NA(),IF(N(D$8)=0,NA(),IF(Inputs!$C$17="Rebased to 100",$D12/D$8*100,$D12))))) | K12: =IF($B12=0,NA(),IF($E12="",NA(),IF(E$8="",NA(),IF(N(E$8)=0,NA(),IF(Inputs!$C$17="Rebased to 100",$E12/E$8*100,$E12))))) | L12: =IF($B12=0,NA(),IF($F12="",NA(),IF(F$8="",NA(),IF(N(F$8)=0,NA(),IF(Inputs!$C$17="Rebased to 100",$F12/F$8*100,$F12))))) | M12: =IF($B12=0,NA(),IF($G12="",NA(),IF(G$8="",NA(),IF(N(G$8)=0,NA(),IF(Inputs!$C$17="Rebased to 100",$G12/G$8*100,$G12))))) | N12: =IF($B12=0,NA(),IF(Inputs!$C$18<>"Yes",NA(),IF(COUNT(I12,J12,K12,L12,M12)=0,NA(),MIN(I12,J12,K12,L12,M12)))) | O12: =IF($B12=0,NA(),IF(Inputs!$B$24<>"Yes",NA(),Inputs!$D$24*Inputs!$C$35)) | P12: =IF($B12=0,NA(),IF(Inputs!$B$25<>"Yes",NA(),Inputs!$D$25*Inputs!$C$35)) | Q12: =IF($B12=0,NA(),IF(Inputs!$B$26<>"Yes",NA(),Inputs!$D$26*Inputs!$C$35)) | R12: =IF($B12=0,NA(),IF(Inputs!$B$27<>"Yes",NA(),Inputs!$D$27*Inputs!$C$35)) | S12: =IF($B12=0,NA(),IF(Inputs!$B$28<>"Yes",NA(),Inputs!$D$28*Inputs!$C$35)) | T12: =IF($B12=0,NA(),IF(Inputs!$B$29<>"Yes",NA(),Inputs!$D$29*Inputs!$C$35)) | AD12: =IF($B12=0,0,IF(Inputs!$B$6="",0,COUNTIFS(Data!$A$10:$A$3209,">="&$A12,Data!$A$10:$A$3209,"<"&$A12+1))) | AE12: =IF($B12=0,0,IF(Inputs!$B$7="",0,COUNTIFS(Data!$E$10:$E$3209,">="&$A12,Data!$E$10:$E$3209,"<"&$A12+1))) | AF12: =IF($B12=0,0,IF(Inputs!$B$8="",0,COUNTIFS(Data!$I$10:$I$3209,">="&$A12,Data!$I$10:$I$3209,"<"&$A12+1))) | AG12: =IF($B12=0,0,IF(Inputs!$B$9="",0,COUNTIFS(Data!$M$10:$M$3209,">="&$A12,Data!$M$10:$M$3209,"<"&$A12+1))) | AH12: =IF($B12=0,0,IF(Inputs!$B$10="",0,COUNTIFS(Data!$Q$10:$Q$3209,">="&$A12,Data!$Q$10:$Q$3209,"<"&$A12+1)))
A13: =MIN(Inputs!$C$15,$A12+IF(WEEKDAY($A12,2)=5,3,1)) | B13: =IF($A13>$A12,1,0) | C13: =IF($B13=0,"",IF(Inputs!$B$6="","",IF($AD13=0,C12,SUMIFS(Data!$B$10:$B$3209,Data!$A$10:$A$3209,">="&$A13,Data!$A$10:$A$3209,"<"&$A13+1)/$AD13))) | D13: =IF($B13=0,"",IF(Inputs!$B$7="","",IF($AE13=0,D12,SUMIFS(Data!$F$10:$F$3209,Data!$E$10:$E$3209,">="&$A13,Data!$E$10:$E$3209,"<"&$A13+1)/$AE13))) | E13: =IF($B13=0,"",IF(Inputs!$B$8="","",IF($AF13=0,E12,SUMIFS(Data!$J$10:$J$3209,Data!$I$10:$I$3209,">="&$A13,Data!$I$10:$I$3209,"<"&$A13+1)/$AF13))) | F13: =IF($B13=0,"",IF(Inputs!$B$9="","",IF($AG13=0,F12,SUMIFS(Data!$N$10:$N$3209,Data!$M$10:$M$3209,">="&$A13,Data!$M$10:$M$3209,"<"&$A13+1)/$AG13))) | G13: =IF($B13=0,"",IF(Inputs!$B$10="","",IF($AH13=0,G12,SUMIFS(Data!$R$10:$R$3209,Data!$Q$10:$Q$3209,">="&$A13,Data!$Q$10:$Q$3209,"<"&$A13+1)/$AH13))) | I13: =IF($B13=0,NA(),IF($C13="",NA(),IF(C$8="",NA(),IF(N(C$8)=0,NA(),IF(Inputs!$C$17="Rebased to 100",$C13/C$8*100,$C13))))) | J13: =IF($B13=0,NA(),IF($D13="",NA(),IF(D$8="",NA(),IF(N(D$8)=0,NA(),IF(Inputs!$C$17="Rebased to 100",$D13/D$8*100,$D13))))) | K13: =IF($B13=0,NA(),IF($E13="",NA(),IF(E$8="",NA(),IF(N(E$8)=0,NA(),IF(Inputs!$C$17="Rebased to 100",$E13/E$8*100,$E13))))) | L13: =IF($B13=0,NA(),IF($F13="",NA(),IF(F$8="",NA(),IF(N(F$8)=0,NA(),IF(Inputs!$C$17="Rebased to 100",$F13/F$8*100,$F13))))) | M13: =IF($B13=0,NA(),IF($G13="",NA(),IF(G$8="",NA(),IF(N(G$8)=0,NA(),IF(Inputs!$C$17="Rebased to 100",$G13/G$8*100,$G13))))) | N13: =IF($B13=0,NA(),IF(Inputs!$C$18<>"Yes",NA(),IF(COUNT(I13,J13,K13,L13,M13)=0,NA(),MIN(I13,J13,K13,L13,M13)))) | O13: =IF($B13=0,NA(),IF(Inputs!$B$24<>"Yes",NA(),Inputs!$D$24*Inputs!$C$35)) | P13: =IF($B13=0,NA(),IF(Inputs!$B$25<>"Yes",NA(),Inputs!$D$25*Inputs!$C$35)) | Q13: =IF($B13=0,NA(),IF(Inputs!$B$26<>"Yes",NA(),Inputs!$D$26*Inputs!$C$35)) | R13: =IF($B13=0,NA(),IF(Inputs!$B$27<>"Yes",NA(),Inputs!$D$27*Inputs!$C$35)) | S13: =IF($B13=0,NA(),IF(Inputs!$B$28<>"Yes",NA(),Inputs!$D$28*Inputs!$C$35)) | T13: =IF($B13=0,NA(),IF(Inputs!$B$29<>"Yes",NA(),Inputs!$D$29*Inputs!$C$35)) | AD13: =IF($B13=0,0,IF(Inputs!$B$6="",0,COUNTIFS(Data!$A$10:$A$3209,">="&$A13,Data!$A$10:$A$3209,"<"&$A13+1))) | AE13: =IF($B13=0,0,IF(Inputs!$B$7="",0,COUNTIFS(Data!$E$10:$E$3209,">="&$A13,Data!$E$10:$E$3209,"<"&$A13+1))) | AF13: =IF($B13=0,0,IF(Inputs!$B$8="",0,COUNTIFS(Data!$I$10:$I$3209,">="&$A13,Data!$I$10:$I$3209,"<"&$A13+1))) | AG13: =IF($B13=0,0,IF(Inputs!$B$9="",0,COUNTIFS(Data!$M$10:$M$3209,">="&$A13,Data!$M$10:$M$3209,"<"&$A13+1))) | AH13: =IF($B13=0,0,IF(Inputs!$B$10="",0,COUNTIFS(Data!$Q$10:$Q$3209,">="&$A13,Data!$Q$10:$Q$3209,"<"&$A13+1)))
A14: =MIN(Inputs!$C$15,$A13+IF(WEEKDAY($A13,2)=5,3,1)) | B14: =IF($A14>$A13,1,0) | C14: =IF($B14=0,"",IF(Inputs!$B$6="","",IF($AD14=0,C13,SUMIFS(Data!$B$10:$B$3209,Data!$A$10:$A$3209,">="&$A14,Data!$A$10:$A$3209,"<"&$A14+1)/$AD14))) | D14: =IF($B14=0,"",IF(Inputs!$B$7="","",IF($AE14=0,D13,SUMIFS(Data!$F$10:$F$3209,Data!$E$10:$E$3209,">="&$A14,Data!$E$10:$E$3209,"<"&$A14+1)/$AE14))) | E14: =IF($B14=0,"",IF(Inputs!$B$8="","",IF($AF14=0,E13,SUMIFS(Data!$J$10:$J$3209,Data!$I$10:$I$3209,">="&$A14,Data!$I$10:$I$3209,"<"&$A14+1)/$AF14))) | F14: =IF($B14=0,"",IF(Inputs!$B$9="","",IF($AG14=0,F13,SUMIFS(Data!$N$10:$N$3209,Data!$M$10:$M$3209,">="&$A14,Data!$M$10:$M$3209,"<"&$A14+1)/$AG14))) | G14: =IF($B14=0,"",IF(Inputs!$B$10="","",IF($AH14=0,G13,SUMIFS(Data!$R$10:$R$3209,Data!$Q$10:$Q$3209,">="&$A14,Data!$Q$10:$Q$3209,"<"&$A14+1)/$AH14))) | I14: =IF($B14=0,NA(),IF($C14="",NA(),IF(C$8="",NA(),IF(N(C$8)=0,NA(),IF(Inputs!$C$17="Rebased to 100",$C14/C$8*100,$C14))))) | J14: =IF($B14=0,NA(),IF($D14="",NA(),IF(D$8="",NA(),IF(N(D$8)=0,NA(),IF(Inputs!$C$17="Rebased to 100",$D14/D$8*100,$D14))))) | K14: =IF($B14=0,NA(),IF($E14="",NA(),IF(E$8="",NA(),IF(N(E$8)=0,NA(),IF(Inputs!$C$17="Rebased to 100",$E14/E$8*100,$E14))))) | L14: =IF($B14=0,NA(),IF($F14="",NA(),IF(F$8="",NA(),IF(N(F$8)=0,NA(),IF(Inputs!$C$17="Rebased to 100",$F14/F$8*100,$F14))))) | M14: =IF($B14=0,NA(),IF($G14="",NA(),IF(G$8="",NA(),IF(N(G$8)=0,NA(),IF(Inputs!$C$17="Rebased to 100",$G14/G$8*100,$G14))))) | N14: =IF($B14=0,NA(),IF(Inputs!$C$18<>"Yes",NA(),IF(COUNT(I14,J14,K14,L14,M14)=0,NA(),MIN(I14,J14,K14,L14,M14)))) | O14: =IF($B14=0,NA(),IF(Inputs!$B$24<>"Yes",NA(),Inputs!$D$24*Inputs!$C$35)) | P14: =IF($B14=0,NA(),IF(Inputs!$B$25<>"Yes",NA(),Inputs!$D$25*Inputs!$C$35)) | Q14: =IF($B14=0,NA(),IF(Inputs!$B$26<>"Yes",NA(),Inputs!$D$26*Inputs!$C$35)) | R14: =IF($B14=0,NA(),IF(Inputs!$B$27<>"Yes",NA(),Inputs!$D$27*Inputs!$C$35)) | S14: =IF($B14=0,NA(),IF(Inputs!$B$28<>"Yes",NA(),Inputs!$D$28*Inputs!$C$35)) | T14: =IF($B14=0,NA(),IF(Inputs!$B$29<>"Yes",NA(),Inputs!$D$29*Inputs!$C$35)) | AD14: =IF($B14=0,0,IF(Inputs!$B$6="",0,COUNTIFS(Data!$A$10:$A$3209,">="&$A14,Data!$A$10:$A$3209,"<"&$A14+1))) | AE14: =IF($B14=0,0,IF(Inputs!$B$7="",0,COUNTIFS(Data!$E$10:$E$3209,">="&$A14,Data!$E$10:$E$3209,"<"&$A14+1))) | AF14: =IF($B14=0,0,IF(Inputs!$B$8="",0,COUNTIFS(Data!$I$10:$I$3209,">="&$A14,Data!$I$10:$I$3209,"<"&$A14+1))) | AG14: =IF($B14=0,0,IF(Inputs!$B$9="",0,COUNTIFS(Data!$M$10:$M$3209,">="&$A14,Data!$M$10:$M$3209,"<"&$A14+1))) | AH14: =IF($B14=0,0,IF(Inputs!$B$10="",0,COUNTIFS(Data!$Q$10:$Q$3209,">="&$A14,Data!$Q$10:$Q$3209,"<"&$A14+1)))
A15: =MIN(Inputs!$C$15,$A14+IF(WEEKDAY($A14,2)=5,3,1)) | B15: =IF($A15>$A14,1,0) | C15: =IF($B15=0,"",IF(Inputs!$B$6="","",IF($AD15=0,C14,SUMIFS(Data!$B$10:$B$3209,Data!$A$10:$A$3209,">="&$A15,Data!$A$10:$A$3209,"<"&$A15+1)/$AD15))) | D15: =IF($B15=0,"",IF(Inputs!$B$7="","",IF($AE15=0,D14,SUMIFS(Data!$F$10:$F$3209,Data!$E$10:$E$3209,">="&$A15,Data!$E$10:$E$3209,"<"&$A15+1)/$AE15))) | E15: =IF($B15=0,"",IF(Inputs!$B$8="","",IF($AF15=0,E14,SUMIFS(Data!$J$10:$J$3209,Data!$I$10:$I$3209,">="&$A15,Data!$I$10:$I$3209,"<"&$A15+1)/$AF15))) | F15: =IF($B15=0,"",IF(Inputs!$B$9="","",IF($AG15=0,F14,SUMIFS(Data!$N$10:$N$3209,Data!$M$10:$M$3209,">="&$A15,Data!$M$10:$M$3209,"<"&$A15+1)/$AG15))) | G15: =IF($B15=0,"",IF(Inputs!$B$10="","",IF($AH15=0,G14,SUMIFS(Data!$R$10:$R$3209,Data!$Q$10:$Q$3209,">="&$A15,Data!$Q$10:$Q$3209,"<"&$A15+1)/$AH15))) | I15: =IF($B15=0,NA(),IF($C15="",NA(),IF(C$8="",NA(),IF(N(C$8)=0,NA(),IF(Inputs!$C$17="Rebased to 100",$C15/C$8*100,$C15))))) | J15: =IF($B15=0,NA(),IF($D15="",NA(),IF(D$8="",NA(),IF(N(D$8)=0,NA(),IF(Inputs!$C$17="Rebased to 100",$D15/D$8*100,$D15))))) | K15: =IF($B15=0,NA(),IF($E15="",NA(),IF(E$8="",NA(),IF(N(E$8)=0,NA(),IF(Inputs!$C$17="Rebased to 100",$E15/E$8*100,$E15))))) | L15: =IF($B15=0,NA(),IF($F15="",NA(),IF(F$8="",NA(),IF(N(F$8)=0,NA(),IF(Inputs!$C$17="Rebased to 100",$F15/F$8*100,$F15))))) | M15: =IF($B15=0,NA(),IF($G15="",NA(),IF(G$8="",NA(),IF(N(G$8)=0,NA(),IF(Inputs!$C$17="Rebased to 100",$G15/G$8*100,$G15))))) | N15: =IF($B15=0,NA(),IF(Inputs!$C$18<>"Yes",NA(),IF(COUNT(I15,J15,K15,L15,M15)=0,NA(),MIN(I15,J15,K15,L15,M15)))) | O15: =IF($B15=0,NA(),IF(Inputs!$B$24<>"Yes",NA(),Inputs!$D$24*Inputs!$C$35)) | P15: =IF($B15=0,NA(),IF(Inputs!$B$25<>"Yes",NA(),Inputs!$D$25*Inputs!$C$35)) | Q15: =IF($B15=0,NA(),IF(Inputs!$B$26<>"Yes",NA(),Inputs!$D$26*Inputs!$C$35)) | R15: =IF($B15=0,NA(),IF(Inputs!$B$27<>"Yes",NA(),Inputs!$D$27*Inputs!$C$35)) | S15: =IF($B15=0,NA(),IF(Inputs!$B$28<>"Yes",NA(),Inputs!$D$28*Inputs!$C$35)) | T15: =IF($B15=0,NA(),IF(Inputs!$B$29<>"Yes",NA(),Inputs!$D$29*Inputs!$C$35)) | AD15: =IF($B15=0,0,IF(Inputs!$B$6="",0,COUNTIFS(Data!$A$10:$A$3209,">="&$A15,Data!$A$10:$A$3209,"<"&$A15+1))) | AE15: =IF($B15=0,0,IF(Inputs!$B$7="",0,COUNTIFS(Data!$E$10:$E$3209,">="&$A15,Data!$E$10:$E$3209,"<"&$A15+1))) | AF15: =IF($B15=0,0,IF(Inputs!$B$8="",0,COUNTIFS(Data!$I$10:$I$3209,">="&$A15,Data!$I$10:$I$3209,"<"&$A15+1))) | AG15: =IF($B15=0,0,IF(Inputs!$B$9="",0,COUNTIFS(Data!$M$10:$M$3209,">="&$A15,Data!$M$10:$M$3209,"<"&$A15+1))) | AH15: =IF($B15=0,0,IF(Inputs!$B$10="",0,COUNTIFS(Data!$Q$10:$Q$3209,">="&$A15,Data!$Q$10:$Q$3209,"<"&$A15+1)))
A16: =MIN(Inputs!$C$15,$A15+IF(WEEKDAY($A15,2)=5,3,1)) | B16: =IF($A16>$A15,1,0) | C16: =IF($B16=0,"",IF(Inputs!$B$6="","",IF($AD16=0,C15,SUMIFS(Data!$B$10:$B$3209,Data!$A$10:$A$3209,">="&$A16,Data!$A$10:$A$3209,"<"&$A16+1)/$AD16))) | D16: =IF($B16=0,"",IF(Inputs!$B$7="","",IF($AE16=0,D15,SUMIFS(Data!$F$10:$F$3209,Data!$E$10:$E$3209,">="&$A16,Data!$E$10:$E$3209,"<"&$A16+1)/$AE16))) | E16: =IF($B16=0,"",IF(Inputs!$B$8="","",IF($AF16=0,E15,SUMIFS(Data!$J$10:$J$3209,Data!$I$10:$I$3209,">="&$A16,Data!$I$10:$I$3209,"<"&$A16+1)/$AF16))) | F16: =IF($B16=0,"",IF(Inputs!$B$9="","",IF($AG16=0,F15,SUMIFS(Data!$N$10:$N$3209,Data!$M$10:$M$3209,">="&$A16,Data!$M$10:$M$3209,"<"&$A16+1)/$AG16))) | G16: =IF($B16=0,"",IF(Inputs!$B$10="","",IF($AH16=0,G15,SUMIFS(Data!$R$10:$R$3209,Data!$Q$10:$Q$3209,">="&$A16,Data!$Q$10:$Q$3209,"<"&$A16+1)/$AH16))) | I16: =IF($B16=0,NA(),IF($C16="",NA(),IF(C$8="",NA(),IF(N(C$8)=0,NA(),IF(Inputs!$C$17="Rebased to 100",$C16/C$8*100,$C16))))) | J16: =IF($B16=0,NA(),IF($D16="",NA(),IF(D$8="",NA(),IF(N(D$8)=0,NA(),IF(Inputs!$C$17="Rebased to 100",$D16/D$8*100,$D16))))) | K16: =IF($B16=0,NA(),IF($E16="",NA(),IF(E$8="",NA(),IF(N(E$8)=0,NA(),IF(Inputs!$C$17="Rebased to 100",$E16/E$8*100,$E16))))) | L16: =IF($B16=0,NA(),IF($F16="",NA(),IF(F$8="",NA(),IF(N(F$8)=0,NA(),IF(Inputs!$C$17="Rebased to 100",$F16/F$8*100,$F16))))) | M16: =IF($B16=0,NA(),IF($G16="",NA(),IF(G$8="",NA(),IF(N(G$8)=0,NA(),IF(Inputs!$C$17="Rebased to 100",$G16/G$8*100,$G16))))) | N16: =IF($B16=0,NA(),IF(Inputs!$C$18<>"Yes",NA(),IF(COUNT(I16,J16,K16,L16,M16)=0,NA(),MIN(I16,J16,K16,L16,M16)))) | O16: =IF($B16=0,NA(),IF(Inputs!$B$24<>"Yes",NA(),Inputs!$D$24*Inputs!$C$35)) | P16: =IF($B16=0,NA(),IF(Inputs!$B$25<>"Yes",NA(),Inputs!$D$25*Inputs!$C$35)) | Q16: =IF($B16=0,NA(),IF(Inputs!$B$26<>"Yes",NA(),Inputs!$D$26*Inputs!$C$35)) | R16: =IF($B16=0,NA(),IF(Inputs!$B$27<>"Yes",NA(),Inputs!$D$27*Inputs!$C$35)) | S16: =IF($B16=0,NA(),IF(Inputs!$B$28<>"Yes",NA(),Inputs!$D$28*Inputs!$C$35)) | T16: =IF($B16=0,NA(),IF(Inputs!$B$29<>"Yes",NA(),Inputs!$D$29*Inputs!$C$35)) | AD16: =IF($B16=0,0,IF(Inputs!$B$6="",0,COUNTIFS(Data!$A$10:$A$3209,">="&$A16,Data!$A$10:$A$3209,"<"&$A16+1))) | AE16: =IF($B16=0,0,IF(Inputs!$B$7="",0,COUNTIFS(Data!$E$10:$E$3209,">="&$A16,Data!$E$10:$E$3209,"<"&$A16+1))) | AF16: =IF($B16=0,0,IF(Inputs!$B$8="",0,COUNTIFS(Data!$I$10:$I$3209,">="&$A16,Data!$I$10:$I$3209,"<"&$A16+1))) | AG16: =IF($B16=0,0,IF(Inputs!$B$9="",0,COUNTIFS(Data!$M$10:$M$3209,">="&$A16,Data!$M$10:$M$3209,"<"&$A16+1))) | AH16: =IF($B16=0,0,IF(Inputs!$B$10="",0,COUNTIFS(Data!$Q$10:$Q$3209,">="&$A16,Data!$Q$10:$Q$3209,"<"&$A16+1)))
A17: =MIN(Inputs!$C$15,$A16+IF(WEEKDAY($A16,2)=5,3,1)) | B17: =IF($A17>$A16,1,0) | C17: =IF($B17=0,"",IF(Inputs!$B$6="","",IF($AD17=0,C16,SUMIFS(Data!$B$10:$B$3209,Data!$A$10:$A$3209,">="&$A17,Data!$A$10:$A$3209,"<"&$A17+1)/$AD17))) | D17: =IF($B17=0,"",IF(Inputs!$B$7="","",IF($AE17=0,D16,SUMIFS(Data!$F$10:$F$3209,Data!$E$10:$E$3209,">="&$A17,Data!$E$10:$E$3209,"<"&$A17+1)/$AE17))) | E17: =IF($B17=0,"",IF(Inputs!$B$8="","",IF($AF17=0,E16,SUMIFS(Data!$J$10:$J$3209,Data!$I$10:$I$3209,">="&$A17,Data!$I$10:$I$3209,"<"&$A17+1)/$AF17))) | F17: =IF($B17=0,"",IF(Inputs!$B$9="","",IF($AG17=0,F16,SUMIFS(Data!$N$10:$N$3209,Data!$M$10:$M$3209,">="&$A17,Data!$M$10:$M$3209,"<"&$A17+1)/$AG17))) | G17: =IF($B17=0,"",IF(Inputs!$B$10="","",IF($AH17=0,G16,SUMIFS(Data!$R$10:$R$3209,Data!$Q$10:$Q$3209,">="&$A17,Data!$Q$10:$Q$3209,"<"&$A17+1)/$AH17))) | I17: =IF($B17=0,NA(),IF($C17="",NA(),IF(C$8="",NA(),IF(N(C$8)=0,NA(),IF(Inputs!$C$17="Rebased to 100",$C17/C$8*100,$C17))))) | J17: =IF($B17=0,NA(),IF($D17="",NA(),IF(D$8="",NA(),IF(N(D$8)=0,NA(),IF(Inputs!$C$17="Rebased to 100",$D17/D$8*100,$D17))))) | K17: =IF($B17=0,NA(),IF($E17="",NA(),IF(E$8="",NA(),IF(N(E$8)=0,NA(),IF(Inputs!$C$17="Rebased to 100",$E17/E$8*100,$E17))))) | L17: =IF($B17=0,NA(),IF($F17="",NA(),IF(F$8="",NA(),IF(N(F$8)=0,NA(),IF(Inputs!$C$17="Rebased to 100",$F17/F$8*100,$F17))))) | M17: =IF($B17=0,NA(),IF($G17="",NA(),IF(G$8="",NA(),IF(N(G$8)=0,NA(),IF(Inputs!$C$17="Rebased to 100",$G17/G$8*100,$G17))))) | N17: =IF($B17=0,NA(),IF(Inputs!$C$18<>"Yes",NA(),IF(COUNT(I17,J17,K17,L17,M17)=0,NA(),MIN(I17,J17,K17,L17,M17)))) | O17: =IF($B17=0,NA(),IF(Inputs!$B$24<>"Yes",NA(),Inputs!$D$24*Inputs!$C$35)) | P17: =IF($B17=0,NA(),IF(Inputs!$B$25<>"Yes",NA(),Inputs!$D$25*Inputs!$C$35)) | Q17: =IF($B17=0,NA(),IF(Inputs!$B$26<>"Yes",NA(),Inputs!$D$26*Inputs!$C$35)) | R17: =IF($B17=0,NA(),IF(Inputs!$B$27<>"Yes",NA(),Inputs!$D$27*Inputs!$C$35)) | S17: =IF($B17=0,NA(),IF(Inputs!$B$28<>"Yes",NA(),Inputs!$D$28*Inputs!$C$35)) | T17: =IF($B17=0,NA(),IF(Inputs!$B$29<>"Yes",NA(),Inputs!$D$29*Inputs!$C$35)) | AD17: =IF($B17=0,0,IF(Inputs!$B$6="",0,COUNTIFS(Data!$A$10:$A$3209,">="&$A17,Data!$A$10:$A$3209,"<"&$A17+1))) | AE17: =IF($B17=0,0,IF(Inputs!$B$7="",0,COUNTIFS(Data!$E$10:$E$3209,">="&$A17,Data!$E$10:$E$3209,"<"&$A17+1))) | AF17: =IF($B17=0,0,IF(Inputs!$B$8="",0,COUNTIFS(Data!$I$10:$I$3209,">="&$A17,Data!$I$10:$I$3209,"<"&$A17+1))) | AG17: =IF($B17=0,0,IF(Inputs!$B$9="",0,COUNTIFS(Data!$M$10:$M$3209,">="&$A17,Data!$M$10:$M$3209,"<"&$A17+1))) | AH17: =IF($B17=0,0,IF(Inputs!$B$10="",0,COUNTIFS(Data!$Q$10:$Q$3209,">="&$A17,Data!$Q$10:$Q$3209,"<"&$A17+1)))
A18: =MIN(Inputs!$C$15,$A17+IF(WEEKDAY($A17,2)=5,3,1)) | B18: =IF($A18>$A17,1,0) | C18: =IF($B18=0,"",IF(Inputs!$B$6="","",IF($AD18=0,C17,SUMIFS(Data!$B$10:$B$3209,Data!$A$10:$A$3209,">="&$A18,Data!$A$10:$A$3209,"<"&$A18+1)/$AD18))) | D18: =IF($B18=0,"",IF(Inputs!$B$7="","",IF($AE18=0,D17,SUMIFS(Data!$F$10:$F$3209,Data!$E$10:$E$3209,">="&$A18,Data!$E$10:$E$3209,"<"&$A18+1)/$AE18))) | E18: =IF($B18=0,"",IF(Inputs!$B$8="","",IF($AF18=0,E17,SUMIFS(Data!$J$10:$J$3209,Data!$I$10:$I$3209,">="&$A18,Data!$I$10:$I$3209,"<"&$A18+1)/$AF18))) | F18: =IF($B18=0,"",IF(Inputs!$B$9="","",IF($AG18=0,F17,SUMIFS(Data!$N$10:$N$3209,Data!$M$10:$M$3209,">="&$A18,Data!$M$10:$M$3209,"<"&$A18+1)/$AG18))) | G18: =IF($B18=0,"",IF(Inputs!$B$10="","",IF($AH18=0,G17,SUMIFS(Data!$R$10:$R$3209,Data!$Q$10:$Q$3209,">="&$A18,Data!$Q$10:$Q$3209,"<"&$A18+1)/$AH18))) | I18: =IF($B18=0,NA(),IF($C18="",NA(),IF(C$8="",NA(),IF(N(C$8)=0,NA(),IF(Inputs!$C$17="Rebased to 100",$C18/C$8*100,$C18))))) | J18: =IF($B18=0,NA(),IF($D18="",NA(),IF(D$8="",NA(),IF(N(D$8)=0,NA(),IF(Inputs!$C$17="Rebased to 100",$D18/D$8*100,$D18))))) | K18: =IF($B18=0,NA(),IF($E18="",NA(),IF(E$8="",NA(),IF(N(E$8)=0,NA(),IF(Inputs!$C$17="Rebased to 100",$E18/E$8*100,$E18))))) | L18: =IF($B18=0,NA(),IF($F18="",NA(),IF(F$8="",NA(),IF(N(F$8)=0,NA(),IF(Inputs!$C$17="Rebased to 100",$F18/F$8*100,$F18))))) | M18: =IF($B18=0,NA(),IF($G18="",NA(),IF(G$8="",NA(),IF(N(G$8)=0,NA(),IF(Inputs!$C$17="Rebased to 100",$G18/G$8*100,$G18))))) | N18: =IF($B18=0,NA(),IF(Inputs!$C$18<>"Yes",NA(),IF(COUNT(I18,J18,K18,L18,M18)=0,NA(),MIN(I18,J18,K18,L18,M18)))) | O18: =IF($B18=0,NA(),IF(Inputs!$B$24<>"Yes",NA(),Inputs!$D$24*Inputs!$C$35)) | P18: =IF($B18=0,NA(),IF(Inputs!$B$25<>"Yes",NA(),Inputs!$D$25*Inputs!$C$35)) | Q18: =IF($B18=0,NA(),IF(Inputs!$B$26<>"Yes",NA(),Inputs!$D$26*Inputs!$C$35)) | R18: =IF($B18=0,NA(),IF(Inputs!$B$27<>"Yes",NA(),Inputs!$D$27*Inputs!$C$35)) | S18: =IF($B18=0,NA(),IF(Inputs!$B$28<>"Yes",NA(),Inputs!$D$28*Inputs!$C$35)) | T18: =IF($B18=0,NA(),IF(Inputs!$B$29<>"Yes",NA(),Inputs!$D$29*Inputs!$C$35)) | AD18: =IF($B18=0,0,IF(Inputs!$B$6="",0,COUNTIFS(Data!$A$10:$A$3209,">="&$A18,Data!$A$10:$A$3209,"<"&$A18+1))) | AE18: =IF($B18=0,0,IF(Inputs!$B$7="",0,COUNTIFS(Data!$E$10:$E$3209,">="&$A18,Data!$E$10:$E$3209,"<"&$A18+1))) | AF18: =IF($B18=0,0,IF(Inputs!$B$8="",0,COUNTIFS(Data!$I$10:$I$3209,">="&$A18,Data!$I$10:$I$3209,"<"&$A18+1))) | AG18: =IF($B18=0,0,IF(Inputs!$B$9="",0,COUNTIFS(Data!$M$10:$M$3209,">="&$A18,Data!$M$10:$M$3209,"<"&$A18+1))) | AH18: =IF($B18=0,0,IF(Inputs!$B$10="",0,COUNTIFS(Data!$Q$10:$Q$3209,">="&$A18,Data!$Q$10:$Q$3209,"<"&$A18+1)))
A19: =MIN(Inputs!$C$15,$A18+IF(WEEKDAY($A18,2)=5,3,1)) | B19: =IF($A19>$A18,1,0) | C19: =IF($B19=0,"",IF(Inputs!$B$6="","",IF($AD19=0,C18,SUMIFS(Data!$B$10:$B$3209,Data!$A$10:$A$3209,">="&$A19,Data!$A$10:$A$3209,"<"&$A19+1)/$AD19))) | D19: =IF($B19=0,"",IF(Inputs!$B$7="","",IF($AE19=0,D18,SUMIFS(Data!$F$10:$F$3209,Data!$E$10:$E$3209,">="&$A19,Data!$E$10:$E$3209,"<"&$A19+1)/$AE19))) | E19: =IF($B19=0,"",IF(Inputs!$B$8="","",IF($AF19=0,E18,SUMIFS(Data!$J$10:$J$3209,Data!$I$10:$I$3209,">="&$A19,Data!$I$10:$I$3209,"<"&$A19+1)/$AF19))) | F19: =IF($B19=0,"",IF(Inputs!$B$9="","",IF($AG19=0,F18,SUMIFS(Data!$N$10:$N$3209,Data!$M$10:$M$3209,">="&$A19,Data!$M$10:$M$3209,"<"&$A19+1)/$AG19))) | G19: =IF($B19=0,"",IF(Inputs!$B$10="","",IF($AH19=0,G18,SUMIFS(Data!$R$10:$R$3209,Data!$Q$10:$Q$3209,">="&$A19,Data!$Q$10:$Q$3209,"<"&$A19+1)/$AH19))) | I19: =IF($B19=0,NA(),IF($C19="",NA(),IF(C$8="",NA(),IF(N(C$8)=0,NA(),IF(Inputs!$C$17="Rebased to 100",$C19/C$8*100,$C19))))) | J19: =IF($B19=0,NA(),IF($D19="",NA(),IF(D$8="",NA(),IF(N(D$8)=0,NA(),IF(Inputs!$C$17="Rebased to 100",$D19/D$8*100,$D19))))) | K19: =IF($B19=0,NA(),IF($E19="",NA(),IF(E$8="",NA(),IF(N(E$8)=0,NA(),IF(Inputs!$C$17="Rebased to 100",$E19/E$8*100,$E19))))) | L19: =IF($B19=0,NA(),IF($F19="",NA(),IF(F$8="",NA(),IF(N(F$8)=0,NA(),IF(Inputs!$C$17="Rebased to 100",$F19/F$8*100,$F19))))) | M19: =IF($B19=0,NA(),IF($G19="",NA(),IF(G$8="",NA(),IF(N(G$8)=0,NA(),IF(Inputs!$C$17="Rebased to 100",$G19/G$8*100,$G19))))) | N19: =IF($B19=0,NA(),IF(Inputs!$C$18<>"Yes",NA(),IF(COUNT(I19,J19,K19,L19,M19)=0,NA(),MIN(I19,J19,K19,L19,M19)))) | O19: =IF($B19=0,NA(),IF(Inputs!$B$24<>"Yes",NA(),Inputs!$D$24*Inputs!$C$35)) | P19: =IF($B19=0,NA(),IF(Inputs!$B$25<>"Yes",NA(),Inputs!$D$25*Inputs!$C$35)) | Q19: =IF($B19=0,NA(),IF(Inputs!$B$26<>"Yes",NA(),Inputs!$D$26*Inputs!$C$35)) | R19: =IF($B19=0,NA(),IF(Inputs!$B$27<>"Yes",NA(),Inputs!$D$27*Inputs!$C$35)) | S19: =IF($B19=0,NA(),IF(Inputs!$B$28<>"Yes",NA(),Inputs!$D$28*Inputs!$C$35)) | T19: =IF($B19=0,NA(),IF(Inputs!$B$29<>"Yes",NA(),Inputs!$D$29*Inputs!$C$35)) | AD19: =IF($B19=0,0,IF(Inputs!$B$6="",0,COUNTIFS(Data!$A$10:$A$3209,">="&$A19,Data!$A$10:$A$3209,"<"&$A19+1))) | AE19: =IF($B19=0,0,IF(Inputs!$B$7="",0,COUNTIFS(Data!$E$10:$E$3209,">="&$A19,Data!$E$10:$E$3209,"<"&$A19+1))) | AF19: =IF($B19=0,0,IF(Inputs!$B$8="",0,COUNTIFS(Data!$I$10:$I$3209,">="&$A19,Data!$I$10:$I$3209,"<"&$A19+1))) | AG19: =IF($B19=0,0,IF(Inputs!$B$9="",0,COUNTIFS(Data!$M$10:$M$3209,">="&$A19,Data!$M$10:$M$3209,"<"&$A19+1))) | AH19: =IF($B19=0,0,IF(Inputs!$B$10="",0,COUNTIFS(Data!$Q$10:$Q$3209,">="&$A19,Data!$Q$10:$Q$3209,"<"&$A19+1)))
A20: =MIN(Inputs!$C$15,$A19+IF(WEEKDAY($A19,2)=5,3,1)) | B20: =IF($A20>$A19,1,0) | C20: =IF($B20=0,"",IF(Inputs!$B$6="","",IF($AD20=0,C19,SUMIFS(Data!$B$10:$B$3209,Data!$A$10:$A$3209,">="&$A20,Data!$A$10:$A$3209,"<"&$A20+1)/$AD20))) | D20: =IF($B20=0,"",IF(Inputs!$B$7="","",IF($AE20=0,D19,SUMIFS(Data!$F$10:$F$3209,Data!$E$10:$E$3209,">="&$A20,Data!$E$10:$E$3209,"<"&$A20+1)/$AE20))) | E20: =IF($B20=0,"",IF(Inputs!$B$8="","",IF($AF20=0,E19,SUMIFS(Data!$J$10:$J$3209,Data!$I$10:$I$3209,">="&$A20,Data!$I$10:$I$3209,"<"&$A20+1)/$AF20))) | F20: =IF($B20=0,"",IF(Inputs!$B$9="","",IF($AG20=0,F19,SUMIFS(Data!$N$10:$N$3209,Data!$M$10:$M$3209,">="&$A20,Data!$M$10:$M$3209,"<"&$A20+1)/$AG20))) | G20: =IF($B20=0,"",IF(Inputs!$B$10="","",IF($AH20=0,G19,SUMIFS(Data!$R$10:$R$3209,Data!$Q$10:$Q$3209,">="&$A20,Data!$Q$10:$Q$3209,"<"&$A20+1)/$AH20))) | I20: =IF($B20=0,NA(),IF($C20="",NA(),IF(C$8="",NA(),IF(N(C$8)=0,NA(),IF(Inputs!$C$17="Rebased to 100",$C20/C$8*100,$C20))))) | J20: =IF($B20=0,NA(),IF($D20="",NA(),IF(D$8="",NA(),IF(N(D$8)=0,NA(),IF(Inputs!$C$17="Rebased to 100",$D20/D$8*100,$D20))))) | K20: =IF($B20=0,NA(),IF($E20="",NA(),IF(E$8="",NA(),IF(N(E$8)=0,NA(),IF(Inputs!$C$17="Rebased to 100",$E20/E$8*100,$E20))))) | L20: =IF($B20=0,NA(),IF($F20="",NA(),IF(F$8="",NA(),IF(N(F$8)=0,NA(),IF(Inputs!$C$17="Rebased to 100",$F20/F$8*100,$F20))))) | M20: =IF($B20=0,NA(),IF($G20="",NA(),IF(G$8="",NA(),IF(N(G$8)=0,NA(),IF(Inputs!$C$17="Rebased to 100",$G20/G$8*100,$G20))))) | N20: =IF($B20=0,NA(),IF(Inputs!$C$18<>"Yes",NA(),IF(COUNT(I20,J20,K20,L20,M20)=0,NA(),MIN(I20,J20,K20,L20,M20)))) | O20: =IF($B20=0,NA(),IF(Inputs!$B$24<>"Yes",NA(),Inputs!$D$24*Inputs!$C$35)) | P20: =IF($B20=0,NA(),IF(Inputs!$B$25<>"Yes",NA(),Inputs!$D$25*Inputs!$C$35)) | Q20: =IF($B20=0,NA(),IF(Inputs!$B$26<>"Yes",NA(),Inputs!$D$26*Inputs!$C$35)) | R20: =IF($B20=0,NA(),IF(Inputs!$B$27<>"Yes",NA(),Inputs!$D$27*Inputs!$C$35)) | S20: =IF($B20=0,NA(),IF(Inputs!$B$28<>"Yes",NA(),Inputs!$D$28*Inputs!$C$35)) | T20: =IF($B20=0,NA(),IF(Inputs!$B$29<>"Yes",NA(),Inputs!$D$29*Inputs!$C$35)) | AD20: =IF($B20=0,0,IF(Inputs!$B$6="",0,COUNTIFS(Data!$A$10:$A$3209,">="&$A20,Data!$A$10:$A$3209,"<"&$A20+1))) | AE20: =IF($B20=0,0,IF(Inputs!$B$7="",0,COUNTIFS(Data!$E$10:$E$3209,">="&$A20,Data!$E$10:$E$3209,"<"&$A20+1))) | AF20: =IF($B20=0,0,IF(Inputs!$B$8="",0,COUNTIFS(Data!$I$10:$I$3209,">="&$A20,Data!$I$10:$I$3209,"<"&$A20+1))) | AG20: =IF($B20=0,0,IF(Inputs!$B$9="",0,COUNTIFS(Data!$M$10:$M$3209,">="&$A20,Data!$M$10:$M$3209,"<"&$A20+1))) | AH20: =IF($B20=0,0,IF(Inputs!$B$10="",0,COUNTIFS(Data!$Q$10:$Q$3209,">="&$A20,Data!$Q$10:$Q$3209,"<"&$A20+1)))
A21: =MIN(Inputs!$C$15,$A20+IF(WEEKDAY($A20,2)=5,3,1)) | B21: =IF($A21>$A20,1,0) | C21: =IF($B21=0,"",IF(Inputs!$B$6="","",IF($AD21=0,C20,SUMIFS(Data!$B$10:$B$3209,Data!$A$10:$A$3209,">="&$A21,Data!$A$10:$A$3209,"<"&$A21+1)/$AD21))) | D21: =IF($B21=0,"",IF(Inputs!$B$7="","",IF($AE21=0,D20,SUMIFS(Data!$F$10:$F$3209,Data!$E$10:$E$3209,">="&$A21,Data!$E$10:$E$3209,"<"&$A21+1)/$AE21))) | E21: =IF($B21=0,"",IF(Inputs!$B$8="","",IF($AF21=0,E20,SUMIFS(Data!$J$10:$J$3209,Data!$I$10:$I$3209,">="&$A21,Data!$I$10:$I$3209,"<"&$A21+1)/$AF21))) | F21: =IF($B21=0,"",IF(Inputs!$B$9="","",IF($AG21=0,F20,SUMIFS(Data!$N$10:$N$3209,Data!$M$10:$M$3209,">="&$A21,Data!$M$10:$M$3209,"<"&$A21+1)/$AG21))) | G21: =IF($B21=0,"",IF(Inputs!$B$10="","",IF($AH21=0,G20,SUMIFS(Data!$R$10:$R$3209,Data!$Q$10:$Q$3209,">="&$A21,Data!$Q$10:$Q$3209,"<"&$A21+1)/$AH21))) | I21: =IF($B21=0,NA(),IF($C21="",NA(),IF(C$8="",NA(),IF(N(C$8)=0,NA(),IF(Inputs!$C$17="Rebased to 100",$C21/C$8*100,$C21))))) | J21: =IF($B21=0,NA(),IF($D21="",NA(),IF(D$8="",NA(),IF(N(D$8)=0,NA(),IF(Inputs!$C$17="Rebased to 100",$D21/D$8*100,$D21))))) | K21: =IF($B21=0,NA(),IF($E21="",NA(),IF(E$8="",NA(),IF(N(E$8)=0,NA(),IF(Inputs!$C$17="Rebased to 100",$E21/E$8*100,$E21))))) | L21: =IF($B21=0,NA(),IF($F21="",NA(),IF(F$8="",NA(),IF(N(F$8)=0,NA(),IF(Inputs!$C$17="Rebased to 100",$F21/F$8*100,$F21))))) | M21: =IF($B21=0,NA(),IF($G21="",NA(),IF(G$8="",NA(),IF(N(G$8)=0,NA(),IF(Inputs!$C$17="Rebased to 100",$G21/G$8*100,$G21))))) | N21: =IF($B21=0,NA(),IF(Inputs!$C$18<>"Yes",NA(),IF(COUNT(I21,J21,K21,L21,M21)=0,NA(),MIN(I21,J21,K21,L21,M21)))) | O21: =IF($B21=0,NA(),IF(Inputs!$B$24<>"Yes",NA(),Inputs!$D$24*Inputs!$C$35)) | P21: =IF($B21=0,NA(),IF(Inputs!$B$25<>"Yes",NA(),Inputs!$D$25*Inputs!$C$35)) | Q21: =IF($B21=0,NA(),IF(Inputs!$B$26<>"Yes",NA(),Inputs!$D$26*Inputs!$C$35)) | R21: =IF($B21=0,NA(),IF(Inputs!$B$27<>"Yes",NA(),Inputs!$D$27*Inputs!$C$35)) | S21: =IF($B21=0,NA(),IF(Inputs!$B$28<>"Yes",NA(),Inputs!$D$28*Inputs!$C$35)) | T21: =IF($B21=0,NA(),IF(Inputs!$B$29<>"Yes",NA(),Inputs!$D$29*Inputs!$C$35)) | AD21: =IF($B21=0,0,IF(Inputs!$B$6="",0,COUNTIFS(Data!$A$10:$A$3209,">="&$A21,Data!$A$10:$A$3209,"<"&$A21+1))) | AE21: =IF($B21=0,0,IF(Inputs!$B$7="",0,COUNTIFS(Data!$E$10:$E$3209,">="&$A21,Data!$E$10:$E$3209,"<"&$A21+1))) | AF21: =IF($B21=0,0,IF(Inputs!$B$8="",0,COUNTIFS(Data!$I$10:$I$3209,">="&$A21,Data!$I$10:$I$3209,"<"&$A21+1))) | AG21: =IF($B21=0,0,IF(Inputs!$B$9="",0,COUNTIFS(Data!$M$10:$M$3209,">="&$A21,Data!$M$10:$M$3209,"<"&$A21+1))) | AH21: =IF($B21=0,0,IF(Inputs!$B$10="",0,COUNTIFS(Data!$Q$10:$Q$3209,">="&$A21,Data!$Q$10:$Q$3209,"<"&$A21+1)))
A22: =MIN(Inputs!$C$15,$A21+IF(WEEKDAY($A21,2)=5,3,1)) | B22: =IF($A22>$A21,1,0) | C22: =IF($B22=0,"",IF(Inputs!$B$6="","",IF($AD22=0,C21,SUMIFS(Data!$B$10:$B$3209,Data!$A$10:$A$3209,">="&$A22,Data!$A$10:$A$3209,"<"&$A22+1)/$AD22))) | D22: =IF($B22=0,"",IF(Inputs!$B$7="","",IF($AE22=0,D21,SUMIFS(Data!$F$10:$F$3209,Data!$E$10:$E$3209,">="&$A22,Data!$E$10:$E$3209,"<"&$A22+1)/$AE22))) | E22: =IF($B22=0,"",IF(Inputs!$B$8="","",IF($AF22=0,E21,SUMIFS(Data!$J$10:$J$3209,Data!$I$10:$I$3209,">="&$A22,Data!$I$10:$I$3209,"<"&$A22+1)/$AF22))) | F22: =IF($B22=0,"",IF(Inputs!$B$9="","",IF($AG22=0,F21,SUMIFS(Data!$N$10:$N$3209,Data!$M$10:$M$3209,">="&$A22,Data!$M$10:$M$3209,"<"&$A22+1)/$AG22))) | G22: =IF($B22=0,"",IF(Inputs!$B$10="","",IF($AH22=0,G21,SUMIFS(Data!$R$10:$R$3209,Data!$Q$10:$Q$3209,">="&$A22,Data!$Q$10:$Q$3209,"<"&$A22+1)/$AH22))) | I22: =IF($B22=0,NA(),IF($C22="",NA(),IF(C$8="",NA(),IF(N(C$8)=0,NA(),IF(Inputs!$C$17="Rebased to 100",$C22/C$8*100,$C22))))) | J22: =IF($B22=0,NA(),IF($D22="",NA(),IF(D$8="",NA(),IF(N(D$8)=0,NA(),IF(Inputs!$C$17="Rebased to 100",$D22/D$8*100,$D22))))) | K22: =IF($B22=0,NA(),IF($E22="",NA(),IF(E$8="",NA(),IF(N(E$8)=0,NA(),IF(Inputs!$C$17="Rebased to 100",$E22/E$8*100,$E22))))) | L22: =IF($B22=0,NA(),IF($F22="",NA(),IF(F$8="",NA(),IF(N(F$8)=0,NA(),IF(Inputs!$C$17="Rebased to 100",$F22/F$8*100,$F22))))) | M22: =IF($B22=0,NA(),IF($G22="",NA(),IF(G$8="",NA(),IF(N(G$8)=0,NA(),IF(Inputs!$C$17="Rebased to 100",$G22/G$8*100,$G22))))) | N22: =IF($B22=0,NA(),IF(Inputs!$C$18<>"Yes",NA(),IF(COUNT(I22,J22,K22,L22,M22)=0,NA(),MIN(I22,J22,K22,L22,M22)))) | O22: =IF($B22=0,NA(),IF(Inputs!$B$24<>"Yes",NA(),Inputs!$D$24*Inputs!$C$35)) | P22: =IF($B22=0,NA(),IF(Inputs!$B$25<>"Yes",NA(),Inputs!$D$25*Inputs!$C$35)) | Q22: =IF($B22=0,NA(),IF(Inputs!$B$26<>"Yes",NA(),Inputs!$D$26*Inputs!$C$35)) | R22: =IF($B22=0,NA(),IF(Inputs!$B$27<>"Yes",NA(),Inputs!$D$27*Inputs!$C$35)) | S22: =IF($B22=0,NA(),IF(Inputs!$B$28<>"Yes",NA(),Inputs!$D$28*Inputs!$C$35)) | T22: =IF($B22=0,NA(),IF(Inputs!$B$29<>"Yes",NA(),Inputs!$D$29*Inputs!$C$35)) | AD22: =IF($B22=0,0,IF(Inputs!$B$6="",0,COUNTIFS(Data!$A$10:$A$3209,">="&$A22,Data!$A$10:$A$3209,"<"&$A22+1))) | AE22: =IF($B22=0,0,IF(Inputs!$B$7="",0,COUNTIFS(Data!$E$10:$E$3209,">="&$A22,Data!$E$10:$E$3209,"<"&$A22+1))) | AF22: =IF($B22=0,0,IF(Inputs!$B$8="",0,COUNTIFS(Data!$I$10:$I$3209,">="&$A22,Data!$I$10:$I$3209,"<"&$A22+1))) | AG22: =IF($B22=0,0,IF(Inputs!$B$9="",0,COUNTIFS(Data!$M$10:$M$3209,">="&$A22,Data!$M$10:$M$3209,"<"&$A22+1))) | AH22: =IF($B22=0,0,IF(Inputs!$B$10="",0,COUNTIFS(Data!$Q$10:$Q$3209,">="&$A22,Data!$Q$10:$Q$3209,"<"&$A22+1)))
A23: =MIN(Inputs!$C$15,$A22+IF(WEEKDAY($A22,2)=5,3,1)) | B23: =IF($A23>$A22,1,0) | C23: =IF($B23=0,"",IF(Inputs!$B$6="","",IF($AD23=0,C22,SUMIFS(Data!$B$10:$B$3209,Data!$A$10:$A$3209,">="&$A23,Data!$A$10:$A$3209,"<"&$A23+1)/$AD23))) | D23: =IF($B23=0,"",IF(Inputs!$B$7="","",IF($AE23=0,D22,SUMIFS(Data!$F$10:$F$3209,Data!$E$10:$E$3209,">="&$A23,Data!$E$10:$E$3209,"<"&$A23+1)/$AE23))) | E23: =IF($B23=0,"",IF(Inputs!$B$8="","",IF($AF23=0,E22,SUMIFS(Data!$J$10:$J$3209,Data!$I$10:$I$3209,">="&$A23,Data!$I$10:$I$3209,"<"&$A23+1)/$AF23))) | F23: =IF($B23=0,"",IF(Inputs!$B$9="","",IF($AG23=0,F22,SUMIFS(Data!$N$10:$N$3209,Data!$M$10:$M$3209,">="&$A23,Data!$M$10:$M$3209,"<"&$A23+1)/$AG23))) | G23: =IF($B23=0,"",IF(Inputs!$B$10="","",IF($AH23=0,G22,SUMIFS(Data!$R$10:$R$3209,Data!$Q$10:$Q$3209,">="&$A23,Data!$Q$10:$Q$3209,"<"&$A23+1)/$AH23))) | I23: =IF($B23=0,NA(),IF($C23="",NA(),IF(C$8="",NA(),IF(N(C$8)=0,NA(),IF(Inputs!$C$17="Rebased to 100",$C23/C$8*100,$C23))))) | J23: =IF($B23=0,NA(),IF($D23="",NA(),IF(D$8="",NA(),IF(N(D$8)=0,NA(),IF(Inputs!$C$17="Rebased to 100",$D23/D$8*100,$D23))))) | K23: =IF($B23=0,NA(),IF($E23="",NA(),IF(E$8="",NA(),IF(N(E$8)=0,NA(),IF(Inputs!$C$17="Rebased to 100",$E23/E$8*100,$E23))))) | L23: =IF($B23=0,NA(),IF($F23="",NA(),IF(F$8="",NA(),IF(N(F$8)=0,NA(),IF(Inputs!$C$17="Rebased to 100",$F23/F$8*100,$F23))))) | M23: =IF($B23=0,NA(),IF($G23="",NA(),IF(G$8="",NA(),IF(N(G$8)=0,NA(),IF(Inputs!$C$17="Rebased to 100",$G23/G$8*100,$G23))))) | N23: =IF($B23=0,NA(),IF(Inputs!$C$18<>"Yes",NA(),IF(COUNT(I23,J23,K23,L23,M23)=0,NA(),MIN(I23,J23,K23,L23,M23)))) | O23: =IF($B23=0,NA(),IF(Inputs!$B$24<>"Yes",NA(),Inputs!$D$24*Inputs!$C$35)) | P23: =IF($B23=0,NA(),IF(Inputs!$B$25<>"Yes",NA(),Inputs!$D$25*Inputs!$C$35)) | Q23: =IF($B23=0,NA(),IF(Inputs!$B$26<>"Yes",NA(),Inputs!$D$26*Inputs!$C$35)) | R23: =IF($B23=0,NA(),IF(Inputs!$B$27<>"Yes",NA(),Inputs!$D$27*Inputs!$C$35)) | S23: =IF($B23=0,NA(),IF(Inputs!$B$28<>"Yes",NA(),Inputs!$D$28*Inputs!$C$35)) | T23: =IF($B23=0,NA(),IF(Inputs!$B$29<>"Yes",NA(),Inputs!$D$29*Inputs!$C$35)) | AD23: =IF($B23=0,0,IF(Inputs!$B$6="",0,COUNTIFS(Data!$A$10:$A$3209,">="&$A23,Data!$A$10:$A$3209,"<"&$A23+1))) | AE23: =IF($B23=0,0,IF(Inputs!$B$7="",0,COUNTIFS(Data!$E$10:$E$3209,">="&$A23,Data!$E$10:$E$3209,"<"&$A23+1))) | AF23: =IF($B23=0,0,IF(Inputs!$B$8="",0,COUNTIFS(Data!$I$10:$I$3209,">="&$A23,Data!$I$10:$I$3209,"<"&$A23+1))) | AG23: =IF($B23=0,0,IF(Inputs!$B$9="",0,COUNTIFS(Data!$M$10:$M$3209,">="&$A23,Data!$M$10:$M$3209,"<"&$A23+1))) | AH23: =IF($B23=0,0,IF(Inputs!$B$10="",0,COUNTIFS(Data!$Q$10:$Q$3209,">="&$A23,Data!$Q$10:$Q$3209,"<"&$A23+1)))
... A2610: =MIN(Inputs!$C$15,$A2609+IF(WEEKDAY($A2609,2)=5,3,1)) | B2610: =IF($A2610>$A2609,1,0) | C2610: =IF($B2610=0,"",IF(Inputs!$B$6="","",IF($AD2610=0,C2609,SUMIFS(Data!$B$10:$B$3209,Data!$A$10:$A$3209,">="&$A2610,Data!$A$10:$A$3209,"<"&$A2610+1)/$AD2610))) | D2610: =IF($B2610=0,"",IF(Inputs!$B$7="","",IF($AE2610=0,D2609,SUMIFS(Data!$F$10:$F$3209,Data!$E$10:$E$3209,">="&$A2610,Data!$E$10:$E$3209,"<"&$A2610+1)/$AE2610))) | E2610: =IF($B2610=0,"",IF(Inputs!$B$8="","",IF($AF2610=0,E2609,SUMIFS(Data!$J$10:$J$3209,Data!$I$10:$I$3209,">="&$A2610,Data!$I$10:$I$3209,"<"&$A2610+1)/$AF2610))) | F2610: =IF($B2610=0,"",IF(Inputs!$B$9="","",IF($AG2610=0,F2609,SUMIFS(Data!$N$10:$N$3209,Data!$M$10:$M$3209,">="&$A2610,Data!$M$10:$M$3209,"<"&$A2610+1)/$AG2610))) | G2610: =IF($B2610=0,"",IF(Inputs!$B$10="","",IF($AH2610=0,G2609,SUMIFS(Data!$R$10:$R$3209,Data!$Q$10:$Q$3209,">="&$A2610,Data!$Q$10:$Q$3209,"<"&$A2610+1)/$AH2610))) | I2610: =IF($B2610=0,NA(),IF($C2610="",NA(),IF(C$8="",NA(),IF(N(C$8)=0,NA(),IF(Inputs!$C$17="Rebased to 100",$C2610/C$8*100,$C2610))))) | J2610: =IF($B2610=0,NA(),IF($D2610="",NA(),IF(D$8="",NA(),IF(N(D$8)=0,NA(),IF(Inputs!$C$17="Rebased to 100",$D2610/D$8*100,$D2610))))) | K2610: =IF($B2610=0,NA(),IF($E2610="",NA(),IF(E$8="",NA(),IF(N(E$8)=0,NA(),IF(Inputs!$C$17="Rebased to 100",$E2610/E$8*100,$E2610))))) | L2610: =IF($B2610=0,NA(),IF($F2610="",NA(),IF(F$8="",NA(),IF(N(F$8)=0,NA(),IF(Inputs!$C$17="Rebased to 100",$F2610/F$8*100,$F2610))))) | M2610: =IF($B2610=0,NA(),IF($G2610="",NA(),IF(G$8="",NA(),IF(N(G$8)=0,NA(),IF(Inputs!$C$17="Rebased to 100",$G2610/G$8*100,$G2610))))) | N2610: =IF($B2610=0,NA(),IF(Inputs!$C$18<>"Yes",NA(),IF(COUNT(I2610,J2610,K2610,L2610,M2610)=0,NA(),MIN(I2610,J2610,K2610,L2610,M2610)))) | O2610: =IF($B2610=0,NA(),IF(Inputs!$B$24<>"Yes",NA(),Inputs!$D$24*Inputs!$C$35)) | P2610: =IF($B2610=0,NA(),IF(Inputs!$B$25<>"Yes",NA(),Inputs!$D$25*Inputs!$C$35)) | Q2610: =IF($B2610=0,NA(),IF(Inputs!$B$26<>"Yes",NA(),Inputs!$D$26*Inputs!$C$35)) | R2610: =IF($B2610=0,NA(),IF(Inputs!$B$27<>"Yes",NA(),Inputs!$D$27*Inputs!$C$35)) | S2610: =IF($B2610=0,NA(),IF(Inputs!$B$28<>"Yes",NA(),Inputs!$D$28*Inputs!$C$35)) | T2610: =IF($B2610=0,NA(),IF(Inputs!$B$29<>"Yes",NA(),Inputs!$D$29*Inputs!$C$35)) | AD2610: =IF($B2610=0,0,IF(Inputs!$B$6="",0,COUNTIFS(Data!$A$10:$A$3209,">="&$A2610,Data!$A$10:$A$3209,"<"&$A2610+1))) | AE2610: =IF($B2610=0,0,IF(Inputs!$B$7="",0,COUNTIFS(Data!$E$10:$E$3209,">="&$A2610,Data!$E$10:$E$3209,"<"&$A2610+1))) | AF2610: =IF($B2610=0,0,IF(Inputs!$B$8="",0,COUNTIFS(Data!$I$10:$I$3209,">="&$A2610,Data!$I$10:$I$3209,"<"&$A2610+1))) | AG2610: =IF($B2610=0,0,IF(Inputs!$B$9="",0,COUNTIFS(Data!$M$10:$M$3209,">="&$A2610,Data!$M$10:$M$3209,"<"&$A2610+1))) | AH2610: =IF($B2610=0,0,IF(Inputs!$B$10="",0,COUNTIFS(Data!$Q$10:$Q$3209,">="&$A2610,Data!$Q$10:$Q$3209,"<"&$A2610+1)))

Sheet Chart
B2: BNP PARIBAS · GLOBAL MARKETS
B3: [ insert the official logo here: Insert > Pictures ]
B36: =Inputs!$C$34
B37: This document is a marketing communication produced by BNP Paribas. It is for information purposes only and does not constitute investment advice, an offer or a solicitation. Simulated or historical levels do not predict future returns. Capital is at risk.

Sheet Formulas
A1: REUTERS / LSEG FORMULAS — REFERENCE
A2: Copy/paste an alternative into row 10 of a Data block if you need a different field or frequency.
A4: WHAT THE FILE USES
B5: Daily close (default) | C5: =@TR(RIC,"TR.PriceClose.date;TR.PriceClose","SDate=<start> EDate=<end> Frq=D CH=Fd RH=IN Null=Skip")
C6: Already in Data!row 10 of every block, with the dates pointing at Inputs!C14 / C15.
A8: ALTERNATIVES
B9: Legacy Eikon (RHistory) | C9: =RHistory(RIC,"TRDPRC_1.CLOSE","START:<start> END:<end> INTERVAL:1D",,"TSREPEAT:NO CH:Fd")
B10: Total return (with dividends) | C10: Replace TR.PriceClose by TR.TotalReturn — better for a fair comparison of several equity underlyings.
B11: Weekly / monthly | C11: Replace Frq=D by Frq=W or Frq=M.
B12: Currency conversion | C12: Add Curn=EUR in the parameter string, e.g. "... Frq=D Curn=EUR CH=Fd RH=IN".
B13: Adjusted close | C13: Use TR.PriceCloseAdjusted if you need capital-event adjusted history.
B14: Intraday / last | C14: =@TR(RIC,"CF_LAST") or =RtGet("IDN",RIC,"CF_LAST") for a live quote (not used for the chart).
A16: COMMON RIC EXAMPLES
B17: Indices | C17: .STOXX50E EURO STOXX 50 · .SPX S&P 500 · .FCHI CAC 40 · .GDAXI DAX · .N225 Nikkei 225 · .HSI Hang Seng · .SX5E is not a RIC — use .STOXX50E
B18: Single stocks | C18: BNPP.PA · MC.PA · SAN.PA · AAPL.O · MSFT.O · SIEGn.DE · NESN.S
B19: Funds / ETF | C19: Use the exchange-listed RIC, e.g. CSPX.L, or the LIPPER RIC for a mutual fund.
A21: TROUBLESHOOTING
B22: NAME error in a block | C22: The LSEG/Refinitiv add-in is not loaded. File > Options > Add-ins > COM Add-ins > tick the LSEG/Eikon/Refinitiv add-in, restart Excel, sign in, then Refresh All.
B23: Empty block | C23: Bad RIC, no entitlement for that instrument, or the period is before the first listing. Check Points loaded / First date on the Inputs sheet.
B24: #RTIC / #WAIT | C24: The request is still running or the RIC is unknown. Wait, then Refresh All again.
B25: Dates look shifted | C25: Your add-in returned an extra column. The block must be: column 1 = date, column 2 = price. Delete the extra column inside the block, or use the RHistory version above.
B26: No add-in at all | C26: Paste your own history straight into the block (column 1 = date, column 2 = close), starting at row 10. Everything else keeps working.
B27: Slow file | C27: Shorten the period on Inputs, or turn off unused underlyings by clearing their RIC.
